lazymappingstorage.py
lazymappingstorage-0.0.2.dist-info/METADATA
lazymappingstorage-0.0.2.dist-info/WHEEL
lazymappingstorage-0.0.2.dist-info/top_level.txt
lazymappingstorage-0.0.2.dist-info/RECORD
