Metadata-Version: 2.1
Name: lazymappingstorage
Version: 0.0.2
Summary: A dict like storage backed by a yaml file or similar method
Home-page: UNKNOWN
Author: Andreas Stephanides
Author-email: st-andreas@gmx.at
License: UNKNOWN
Platform: UNKNOWN
Requires-Dist: PyYAML
Provides-Extra: dev
Requires-Dist: pytest (>=3.7) ; extra == 'dev'
